{
	"handles": {
		"okaxis": {"provider_name": "Axis Bank", "provider_type": "bank"},
		"okhdfcbank": {"provider_name": "HDFC Bank", "provider_type": "bank"},
		"okicici": {"provider_name": "ICICI Bank", "provider_type": "bank"},
		"oksbi": {"provider_name": "State Bank of India", "provider_type": "bank"},
		"ybl": {"provider_name": "Yes Bank", "provider_type": "bank"},
		"apl": {"provider_name": "Axis Bank (PhonePe PSP)", "provider_type": "psp"},
		"paytm": {"provider_name": "Paytm Payments Bank", "provider_type": "psp"},
		"ptyes": {"provider_name": "Paytm via Yes Bank", "provider_type": "psp"},
		"upi": {"provider_name": "BHIM UPI Generic Handle", "provider_type": "network"},
		"ibl": {"provider_name": "IDBI Bank", "provider_type": "bank"},
		"cnrb": {"provider_name": "Canara Bank", "provider_type": "bank"},
		"barodampay": {"provider_name": "Bank of Baroda", "provider_type": "bank"},
		"fbl": {"provider_name": "Federal Bank", "provider_type": "bank"},
		"kotak": {"provider_name": "Kotak Mahindra Bank", "provider_type": "bank"},
		"kmb": {"provider_name": "Kotak Mahindra Bank", "provider_type": "bank"},
		"kmbl": {"provider_name": "Kotak Mahindra Bank", "provider_type": "bank"},
		"jsb": {"provider_name": "Jana Small Finance Bank", "provider_type": "bank"},
		"pnb": {"provider_name": "Punjab National Bank", "provider_type": "bank"},
		"ubi": {"provider_name": "Union Bank of India", "provider_type": "bank"},
		"unionbank": {"provider_name": "Union Bank of India", "provider_type": "bank"},
		"utib": {"provider_name": "Axis Bank", "provider_type": "bank"},
		"axisbank": {"provider_name": "Axis Bank", "provider_type": "bank"},
		"hdfcbank": {"provider_name": "HDFC Bank", "provider_type": "bank"},
		"icici": {"provider_name": "ICICI Bank", "provider_type": "bank"},
		"sbi": {"provider_name": "State Bank of India", "provider_type": "bank"},
		"aubank": {"provider_name": "AU Small Finance Bank", "provider_type": "bank"},
		"cub": {"provider_name": "City Union Bank", "provider_type": "bank"},
		"dlb": {"provider_name": "Dhanlaxmi Bank", "provider_type": "bank"},
		"equitas": {"provider_name": "Equitas Small Finance Bank", "provider_type": "bank"},
		"esaf": {"provider_name": "ESAF Small Finance Bank", "provider_type": "bank"},
		"idbi": {"provider_name": "IDBI Bank", "provider_type": "bank"},
		"idfcbank": {"provider_name": "IDFC FIRST Bank", "provider_type": "bank"},
		"jkb": {"provider_name": "Jammu and Kashmir Bank", "provider_type": "bank"},
		"kvb": {"provider_name": "Karur Vysya Bank", "provider_type": "bank"},
		"lvb": {"provider_name": "Lakshmi Vilas Bank", "provider_type": "bank"},
		"nsdl": {"provider_name": "NSDL Payments Bank", "provider_type": "bank"},
		"rbl": {"provider_name": "RBL Bank", "provider_type": "bank"},
		"scb": {"provider_name": "Standard Chartered Bank", "provider_type": "bank"},
		"tjsb": {"provider_name": "TJSB Sahakari Bank", "provider_type": "bank"},
		"ujjivan": {"provider_name": "Ujjivan Small Finance Bank", "provider_type": "bank"},
		"yes": {"provider_name": "Yes Bank", "provider_type": "bank"},
		"airtel": {"provider_name": "Airtel Payments Bank", "provider_type": "bank"},
		"axl": {"provider_name": "Axis Bank Limited", "provider_type": "bank"},
		"abfspay": {"provider_name": "Aditya Birla Finance", "provider_type": "psp"},
		"freecharge": {"provider_name": "Freecharge", "provider_type": "psp"},
		"amazonpay": {"provider_name": "Amazon Pay", "provider_type": "psp"},
		"mobikwik": {"provider_name": "MobiKwik", "provider_type": "psp"}
	}
}

